dmsa/__init__.py
dmsa/ddl.py
dmsa/erd.py
dmsa/main.py
dmsa/makers.py
dmsa/service.py
dmsa/utility.py
dmsa/templates/index.html
dmsa/templates/model.html
dmsa/templates/version.html
dmsa/tests/__init__.py
dmsa/tests/container_integration.py
dmsa/tests/output_all_ddl.py
dmsa/tests/test_ddl.py
dmsa/tests/test_erd.py
dmsa/tests/test_make_column.py
dmsa/tests/test_make_constraint.py
dmsa/tests/test_make_index.py
dmsa/tests/test_make_model.py
dmsa/tests/test_make_model_from_service.py
dmsa/tests/test_make_table.py
dmsa/tests/test_service.py
dmsa-0.5.8.dist-info/DESCRIPTION.rst
dmsa-0.5.8.dist-info/METADATA
dmsa-0.5.8.dist-info/RECORD
dmsa-0.5.8.dist-info/WHEEL
dmsa-0.5.8.dist-info/entry_points.txt
dmsa-0.5.8.dist-info/metadata.json
dmsa-0.5.8.dist-info/top_level.txt
