Metadata-Version: 2.0
Name: dmsa
Version: 0.5.8
Summary: SQLAlchemy models and DDL and ERD generation from chop-dbhi/data-models style JSON endpoints.
Home-page: https://github.com/chop-dbhi/data-models-sqlalchemy
Author: The Children's Hospital of Philadelphia
Author-email: cbmisupport@email.chop.edu
License: Other/Proprietary
Download-URL: https://github.com/chop-dbhi/data-models-sqlalchemy/tarball/0.5.8
Keywords: healthcare,data models,SQLAlchemy,DDL,ERD
Platform: UNKNOWN
Classifier: Development Status :: 4 - Beta
Classifier: Programming Language :: Python
Classifier: Programming Language :: Python :: 2.7
Classifier: Intended Audience :: Developers
Classifier: Intended Audience :: Science/Research
Classifier: Intended Audience :: Healthcare Industry
Classifier: License :: Other/Proprietary License
Classifier: Topic :: Database
Classifier: Topic :: Scientific/Engineering :: Information Analysis
Classifier: Topic :: Scientific/Engineering :: Visualization
Classifier: Topic :: Software Development :: Libraries :: Python Modules
Classifier: Topic :: Software Development :: Code Generators
Classifier: Natural Language :: English
Requires-Dist: ERAlchemy (==0.0.28)
Requires-Dist: Flask (==0.10.1)
Requires-Dist: SQLAlchemy (==1.0.5)
Requires-Dist: docopt (==0.6.2)
Requires-Dist: requests (==2.7.0)
